earwigbot/__init__.py
earwigbot/bot.py
earwigbot/cli.py
earwigbot/exceptions.py
earwigbot/managers.py
earwigbot/commands/__init__.py
earwigbot/commands/access.py
earwigbot/commands/calc.py
earwigbot/commands/chanops.py
earwigbot/commands/cidr.py
earwigbot/commands/crypt.py
earwigbot/commands/ctcp.py
earwigbot/commands/dictionary.py
earwigbot/commands/editcount.py
earwigbot/commands/help.py
earwigbot/commands/lag.py
earwigbot/commands/langcode.py
earwigbot/commands/link.py
earwigbot/commands/notes.py
earwigbot/commands/quit.py
earwigbot/commands/registration.py
earwigbot/commands/remind.py
earwigbot/commands/rights.py
earwigbot/commands/stalk.py
earwigbot/commands/test.py
earwigbot/commands/threads.py
earwigbot/commands/time_command.py
earwigbot/commands/trout.py
earwigbot/commands/watchers.py
earwigbot/config/__init__.py
earwigbot/config/formatter.py
earwigbot/config/node.py
earwigbot/config/permissions.py
earwigbot/config/script.py
earwigbot/irc/__init__.py
earwigbot/irc/connection.py
earwigbot/irc/data.py
earwigbot/irc/frontend.py
earwigbot/irc/rc.py
earwigbot/irc/watcher.py
earwigbot/tasks/__init__.py
earwigbot/tasks/wikiproject_tagger.py
earwigbot/wiki/__init__.py
earwigbot/wiki/category.py
earwigbot/wiki/constants.py
earwigbot/wiki/page.py
earwigbot/wiki/site.py
earwigbot/wiki/sitesdb.py
earwigbot/wiki/user.py
earwigbot/wiki/copyvios/__init__.py
earwigbot/wiki/copyvios/exclusions.py
earwigbot/wiki/copyvios/markov.py
earwigbot/wiki/copyvios/parsers.py
earwigbot/wiki/copyvios/result.py
earwigbot/wiki/copyvios/search.py
earwigbot/wiki/copyvios/workers.py
earwigbot-0.4.dist-info/LICENSE
earwigbot-0.4.dist-info/METADATA
earwigbot-0.4.dist-info/WHEEL
earwigbot-0.4.dist-info/entry_points.txt
earwigbot-0.4.dist-info/top_level.txt
earwigbot-0.4.dist-info/RECORD
