Metadata-Version: 2.1
Name: earwigbot
Version: 0.4
Summary: EarwigBot is a bot that edits Wikipedia and interacts over IRC
Author-email: Ben Kurtovic <ben@benkurtovic.com>
Project-URL: Homepage, https://github.com/earwig/earwigbot
Project-URL: Documentation, https://pythonhosted.org/earwigbot/
Project-URL: Issues, https://github.com/earwig/earwigbot/issues
Project-URL: Changelog, https://github.com/earwig/earwigbot/blob/main/CHANGELOG
Keywords: earwig,earwigbot,irc,wikipedia,wiki,mediawiki
Classifier: Development Status :: 3 - Alpha
Classifier: Environment :: Console
Classifier: Intended Audience :: Developers
Classifier: License :: OSI Approved :: MIT License
Classifier: Natural Language :: English
Classifier: Operating System :: OS Independent
Classifier: Programming Language :: Python :: 3
Classifier: Topic :: Communications :: Chat :: Internet Relay Chat
Classifier: Topic :: Internet :: WWW/HTTP
Requires-Python: >=3.11
License-File: LICENSE
Requires-Dist: PyYAML >=5.4.1
Requires-Dist: mwparserfromhell >=0.6
Requires-Dist: requests >=2.25.1
Requires-Dist: requests-oauthlib >=1.3.0
Provides-Extra: copyvios
Requires-Dist: beautifulsoup4 >=4.9.3 ; extra == 'copyvios'
Requires-Dist: charset-normalizer >=3.3.2 ; extra == 'copyvios'
Requires-Dist: lxml >=4.6.3 ; extra == 'copyvios'
Requires-Dist: nltk >=3.6.1 ; extra == 'copyvios'
Requires-Dist: pdfminer >=20191125 ; extra == 'copyvios'
Requires-Dist: tldextract >=3.1.0 ; extra == 'copyvios'
Provides-Extra: crypto
Requires-Dist: cryptography >=3.4.7 ; extra == 'crypto'
Provides-Extra: dev
Requires-Dist: pytest >=8.3.1 ; extra == 'dev'
Provides-Extra: sql
Requires-Dist: pymysql >=1.1.0 ; extra == 'sql'
